pysolarmanv5/__init__.py
pysolarmanv5/pysolarmanv5.py
pysolarmanv5/pysolarmanv5_async.py
zem_pysolarmanv5-2.5.0rc2.dist-info/LICENSE
zem_pysolarmanv5-2.5.0rc2.dist-info/METADATA
zem_pysolarmanv5-2.5.0rc2.dist-info/WHEEL
zem_pysolarmanv5-2.5.0rc2.dist-info/top_level.txt
zem_pysolarmanv5-2.5.0rc2.dist-info/RECORD
